[
  {
    "key": "gulp",
    "title": "Gulp",
    "logo": "https://gfulton-images.s3.amazonaws.com/2015/Dec/gulp_logo-1450648879924.jpg",
    "text1": "The streaming build system",
    "text2": "Automate and enhance your workflow"
  },
  {
    "key": "angular1",
    "title": "Angular 1",
    "logo": "http://www.w3schools.com/angular/pic_angular.jpg",
    "text1": "HTML enhanced for web apps!",
    "text2": "AngularJS lets you extend HTML vocabulary for your application. The resulting environment is extraordinarily expressive, readable, and quick to develop."
  }
]
